setup.py
nlp_utils_ch/__init__.py
nlp_utils_ch/index.py
nlp_utils_ch.egg-info/PKG-INFO
nlp_utils_ch.egg-info/SOURCES.txt
nlp_utils_ch.egg-info/dependency_links.txt
nlp_utils_ch.egg-info/requires.txt
nlp_utils_ch.egg-info/top_level.txt
nlp_utils_ch/char_judgement/__init__.py
nlp_utils_ch/char_judgement/char_judgement.py
nlp_utils_ch/data_process/__init__.py
nlp_utils_ch/data_process/csv_process.py
nlp_utils_ch/data_process/file_convert.py
nlp_utils_ch/data_process/json_process.py
nlp_utils_ch/data_process/read_table_data.py
nlp_utils_ch/data_process/txt_process.py
nlp_utils_ch/flash_text/__init__.py
nlp_utils_ch/flash_text/keyword.py
nlp_utils_ch/resources/stopwords.txt
nlp_utils_ch/resources/symbol.txt
nlp_utils_ch/result_analysis/__init__.py
nlp_utils_ch/result_analysis/classification_result.py
nlp_utils_ch/result_analysis/ner_result.py
nlp_utils_ch/result_analysis/pyrouge_metric.py
nlp_utils_ch/result_analysis/rouge_metric.py
nlp_utils_ch/scel_to_txt/__init__.py
nlp_utils_ch/scel_to_txt/scel2txt.py
nlp_utils_ch/text_clean/__init__.py
nlp_utils_ch/text_clean/filter_text.py
nlp_utils_ch/text_clean/position_process.py
nlp_utils_ch/text_clean/prefix_suffix_process.py
nlp_utils_ch/text_clean/strQ2B.py
nlp_utils_ch/text_clean/text_preprocess.py
nlp_utils_ch/text_clean/text_tokenize.py
nlp_utils_ch/torch_snippet/__init__.py
nlp_utils_ch/torch_snippet/parameter_process.py
nlp_utils_ch/utils/__init__.py
nlp_utils_ch/utils/ac_keyword_processor.py
nlp_utils_ch/utils/file_process.py
nlp_utils_ch/utils/logger.py
nlp_utils_ch/utils/math_op.py
nlp_utils_ch/utils/md5_process.py
nlp_utils_ch/utils/mysql_process.py
nlp_utils_ch/utils/show.py
nlp_utils_ch/utils/stop_words.py
nlp_utils_ch/utils/text_process.py
nlp_utils_ch/utils/time_process.py
nlp_utils_ch/utils/time_tranform.py
nlp_utils_ch/utils/time_utils.py
nlp_utils_ch/utils/timeout_process.py
nlp_utils_ch/utils/util.py
nlp_utils_ch/zhconv/__init__.py
nlp_utils_ch/zhconv/__main__.py
nlp_utils_ch/zhconv/zhcdict.json
nlp_utils_ch/zhconv/zhconv.py