Metadata-Version: 1.0
Name: nlp-utils-ch
Version: 1.1.4
Summary: nlp基础工具
Home-page: UNKNOWN
Author: peng.su
Author-email: alweeq5@163.com
License: UNKNOWN
Platform: UNKNOWN
